user_list/__init__.py
user_list/main.py
user_list/requirements.txt
user_list-0.1.0.dist-info/WHEEL
user_list-0.1.0.dist-info/METADATA
user_list-0.1.0.dist-info/RECORD
