Metadata-Version: 2.1
Name: user-list
Version: 0.1.0
Summary: Package to create a CSV or HTML file for a determine url.
License: MIT
Author: Asdrubal Gonzalez Penton
Author-email: agpenton@gmail.com
Requires-Python: >=3.9,<4.0
Classifier: License :: OSI Approved :: MIT License
Classifier: Programming Language :: Python :: 3
Classifier: Programming Language :: Python :: 3.9
Classifier: Programming Language :: Python :: 3.10
Requires-Dist: argparse (>=1.4.0,<2.0.0)
Requires-Dist: pandas (>=1.5.0,<2.0.0)
Requires-Dist: requests (>=2.28.1,<3.0.0)
